casedev/__init__.py
casedev/_base_client.py
casedev/_client.py
casedev/_compat.py
casedev/_constants.py
casedev/_exceptions.py
casedev/_files.py
casedev/_models.py
casedev/_qs.py
casedev/_resource.py
casedev/_response.py
casedev/_streaming.py
casedev/_types.py
casedev/_version.py
casedev/py.typed
casedev/_utils/__init__.py
casedev/_utils/_compat.py
casedev/_utils/_datetime_parse.py
casedev/_utils/_json.py
casedev/_utils/_logs.py
casedev/_utils/_proxy.py
casedev/_utils/_reflection.py
casedev/_utils/_resources_proxy.py
casedev/_utils/_streams.py
casedev/_utils/_sync.py
casedev/_utils/_transform.py
casedev/_utils/_typing.py
casedev/_utils/_utils.py
casedev/lib/.keep
casedev/resources/__init__.py
casedev/resources/compute/__init__.py
casedev/resources/compute/compute.py
casedev/resources/compute/v1/__init__.py
casedev/resources/compute/v1/environments.py
casedev/resources/compute/v1/secrets.py
casedev/resources/compute/v1/v1.py
casedev/resources/format/__init__.py
casedev/resources/format/format.py
casedev/resources/format/v1/__init__.py
casedev/resources/format/v1/templates.py
casedev/resources/format/v1/v1.py
casedev/resources/llm/__init__.py
casedev/resources/llm/llm.py
casedev/resources/llm/v1/__init__.py
casedev/resources/llm/v1/chat.py
casedev/resources/llm/v1/v1.py
casedev/resources/ocr/__init__.py
casedev/resources/ocr/ocr.py
casedev/resources/ocr/v1.py
casedev/resources/search/__init__.py
casedev/resources/search/search.py
casedev/resources/search/v1.py
casedev/resources/vault/__init__.py
casedev/resources/vault/graphrag.py
casedev/resources/vault/objects.py
casedev/resources/vault/vault.py
casedev/resources/voice/__init__.py
casedev/resources/voice/streaming.py
casedev/resources/voice/transcription.py
casedev/resources/voice/voice.py
casedev/resources/voice/v1/__init__.py
casedev/resources/voice/v1/speak.py
casedev/resources/voice/v1/v1.py
casedev/types/__init__.py
casedev/types/llm_get_config_response.py
casedev/types/vault_create_params.py
casedev-0.3.0.dist-info/METADATA
casedev-0.3.0.dist-info/WHEEL
casedev-0.3.0.dist-info/licenses/LICENSE
casedev-0.3.0.dist-info/RECORD
